vchat/.gitignore
vchat/__init__.py
vchat/_version.py
vchat/config.py
vchat/errors.py
vchat/utils.py
vchat/core/__init__.py
vchat/core/contact.py
vchat/core/core.py
vchat/core/hotreload.py
vchat/core/interface.py
vchat/core/login.py
vchat/core/messages.py
vchat/core/register.py
vchat/core/utils.py
vchat/model/__init__.py
vchat/model/contact.py
vchat/model/content.py
vchat/model/message.py
vchat/net/__init__.py
vchat/net/chatroom.py
vchat/net/download.py
vchat/net/friend.py
vchat/net/interface.py
vchat/net/login.py
vchat/net/net_helper.py
vchat/net/send.py
vchat/net/update.py
vchat/storage/__init__.py
vchat/storage/login_info.py
VChat-1.2.0.dist-info/LICENSE
VChat-1.2.0.dist-info/METADATA
VChat-1.2.0.dist-info/WHEEL
VChat-1.2.0.dist-info/top_level.txt
VChat-1.2.0.dist-info/RECORD
