Metadata-Version: 2.1
Name: VChat
Version: 1.2.0
Summary: A wechat personal account interface
Author-email: z2z63 <vituralfuture@gmail.com>
License: MIT License
Project-URL: Homepage, https://github.com/z2z63/VChat
Project-URL: Issues, https://github.com/z2z63/VChat/issues
Keywords: wechat,wexin,itchat,itchat-uos
Classifier: Programming Language :: Python :: 3
Classifier: License :: OSI Approved :: MIT License
Classifier: Operating System :: OS Independent
Requires-Python: >=3.10
License-File: LICENSE
Requires-Dist: pyqrcode~=1.2.1
Requires-Dist: aiohttp~=3.9.1
Requires-Dist: yarl~=1.9.4
Requires-Dist: lxml~=5.2.2
Requires-Dist: typing-extensions; python_version < "3.12"
